[
  {
  "title":"The Internet Police: How Crime Went Online, and the Cops Followed",
  "authors":["Nate Anderson"],
  "image":"http://www.jordans.com/~/media/Jordans%20Redesign/No-image-found.jpg"
  }, {
  "title":"Countdown to Zero Day: Stuxnet and the Launch of the World's First Digital Weapon",
  "authors":["Kim Zetter"],
  "image":"http://www.jordans.com/~/media/Jordans%20Redesign/No-image-found.jpg"
  }, {
  "title":"A PhD Is Not Enough!: A Guide to Survival in Science",
  "authors":["Peter J Feibelman"],
  "image":"http://www.jordans.com/~/media/Jordans%20Redesign/No-image-found.jpg"
  }, {
  "title":"The One World Schoolhouse: Education Reimagined",
  "authors":["Salman Khan"],
  "image":"http://www.jordans.com/~/media/Jordans%20Redesign/No-image-found.jpg"
  }, {
  "title":"Who Owns the Future?",
  "authors":["Jaron Lanier"],
  "image":"http://www.jordans.com/~/media/Jordans%20Redesign/No-image-found.jpg"
  }, {
  "title":"Digital Cosmopolitans: Why We Think the Internet Connects Us, Why It Doesn't, and How to Rewire It",
  "authors":["Ethan Zuckerman"],
  "image":"http://www.jordans.com/~/media/Jordans%20Redesign/No-image-found.jpg"
  }, {
  "title":"Numbersense: How to Use Big Data to Your Advantage",
  "authors":["Kaiser Fung"],
  "image":"http://www.jordans.com/~/media/Jordans%20Redesign/No-image-found.jpg"
  }, {
  "title":"Cities Are Good for You: The Genius of the Metropolis",
  "authors":["Leo Hollis"],
  "image":"http://www.jordans.com/~/media/Jordans%20Redesign/No-image-found.jpg"
  }, {
  "title":"Biological Anthropology",
  "authors":["Michael Park"],
  "image":"http://www.jordans.com/~/media/Jordans%20Redesign/No-image-found.jpg"
  }, {
  "title":"Physical Anthropology",
  "authors":["Philip L. Stein","Bruce M. Rowe"],
  "image":"http://www.jordans.com/~/media/Jordans%20Redesign/No-image-found.jpg"
  }, {
  "title":"Images of the Past",
  "authors":["T. Douglas Price","Gary Feinman"],
  "image":"http://www.jordans.com/~/media/Jordans%20Redesign/No-image-found.jpg"
  }, {
  "title":"Development and Underdevelopment: The Political Economy of Global Inequality",
  "authors":["Mitchell A. Seligson","John T Passé-Smith"],
  "image":"http://www.jordans.com/~/media/Jordans%20Redesign/No-image-found.jpg"
  }, {
  "title":"The Age of the Economist",
  "authors":["Daniel R. Fusfeld"],
  "image":"http://www.jordans.com/~/media/Jordans%20Redesign/No-image-found.jpg"
  }, {
  "title":"Global Political Economy",
  "authors":["Theodore Cohn"],
  "image":"http://www.jordans.com/~/media/Jordans%20Redesign/No-image-found.jpg"
  }, {
  "title":"Common Wealth: Economics for a Crowded Planet",
  "authors":["Jeffrey D. Sachs"],
  "image":"http://www.jordans.com/~/media/Jordans%20Redesign/No-image-found.jpg"
  }, {
  "title":"International Political Economy State-Market Relations in a Changing Global Order",
  "authors":["Goddard C. Roe","Cronin Patrick"],
  "image":"http://www.jordans.com/~/media/Jordans%20Redesign/No-image-found.jpg"
  }, {
  "title":"Macroeconomics",
  "authors":["David Colander"],
  "image":"http://www.jordans.com/~/media/Jordans%20Redesign/No-image-found.jpg"
  }, {
  "title":"Microeconomics",
  "authors":["David Colander"],
  "image":"http://www.jordans.com/~/media/Jordans%20Redesign/No-image-found.jpg"
  }, {
  "title":"Voyages to the Planets",
  "authors":["Andrew Fraknoi","David Morrison"],
  "image":"http://www.jordans.com/~/media/Jordans%20Redesign/No-image-found.jpg"
  }, {
  "title":"Voyages to the Stars and Galaxies",
  "authors":["Andrew Fraknoi","David Morrison"],
  "image":"http://www.jordans.com/~/media/Jordans%20Redesign/No-image-found.jpg"
  }, {
  "title":"Leadership at a Distance: Research in Technologically-Supported Work",
  "authors":["Suzanne P. Weisband"],
  "image":"http://www.jordans.com/~/media/Jordans%20Redesign/No-image-found.jpg"
  }, {
  "title":"Design for Hackers: Reverse Engineering Beauty",
  "authors":["David Kadavy"],
  "image":"http://www.jordans.com/~/media/Jordans%20Redesign/No-image-found.jpg"
  }, {
  "title":"Priests and Programmers: Technologies of Power in the Engineered Landscape of Bali",
  "authors":["J. Stephen Lansing","William C. Clark"],
  "image":"http://www.jordans.com/~/media/Jordans%20Redesign/No-image-found.jpg"
  }, {
  "title":"Thinking, Fast and Slow",
  "authors":["Daniel Kahneman"],
  "image":"http://www.jordans.com/~/media/Jordans%20Redesign/No-image-found.jpg"
  }, {
  "title":"Cold War, Cool Medium: Television, McCarthyism, and American Culture",
  "authors":["Thomas Doherty"],
  "image":"http://www.jordans.com/~/media/Jordans%20Redesign/No-image-found.jpg"
  }, {
  "title":"The World of the Ancient Maya",
  "authors":["John S. Henderson"],
  "image":"http://www.jordans.com/~/media/Jordans%20Redesign/No-image-found.jpg"
  }, {
  "title":"Gödel, Escher, Bach: An Eternal Golden Braid",
  "authors":["Douglas R. Hofstadter"],
  "image":"http://www.jordans.com/~/media/Jordans%20Redesign/No-image-found.jpg"
  }, {
  "title":"Castes of Mind: Colonialism and the Making of Modern India",
  "authors":["Nicholas B. Dirks"],
  "image":"http://www.jordans.com/~/media/Jordans%20Redesign/No-image-found.jpg"
  }, {
  "title":"Mexico: From the Olmecs to the Aztecs",
  "authors":["Michael D. Coe","Rex Koontz"],
  "image":"http://www.jordans.com/~/media/Jordans%20Redesign/No-image-found.jpg"
  }, {
  "title":"Big Structures, Large Processes, Huge Comparisons",
  "authors":["Charles Tilly"],
  "image":"http://www.jordans.com/~/media/Jordans%20Redesign/No-image-found.jpg"
  }, {
  "title":"The Ghosts of Europe: Central Europe's Past and Uncertain Future",
  "authors":["Anna Porter"],
  "image":"http://www.jordans.com/~/media/Jordans%20Redesign/No-image-found.jpg"
  }, {
  "title":"Everyday Life in Central Asia: Past and Present",
  "authors":["Jeff Sahadeo","Russell Zanca"],
  "image":"http://www.jordans.com/~/media/Jordans%20Redesign/No-image-found.jpg"
  }, {
  "title":"Magic Witchcraft and Religion: A Reader in the Anthropology of Religion",
  "authors":["Pamela Moro","James Myers"],
  "image":"http://www.jordans.com/~/media/Jordans%20Redesign/No-image-found.jpg"
  }, {
  "title":"Conformity and Conflict: Readings in Cultural Anthropology",
  "authors":["James W. Spradley","David W. McCurdy"],
  "image":"http://www.jordans.com/~/media/Jordans%20Redesign/No-image-found.jpg"
  }, {
  "title":"Social and Personal Ethics",
  "authors":["William H. Shaw"],
  "image":"http://www.jordans.com/~/media/Jordans%20Redesign/No-image-found.jpg"
  }, {
  "title":"Perspectives on Current Social Problems",
  "authors":["Gregg Lee Carter"],
  "image":"http://www.jordans.com/~/media/Jordans%20Redesign/No-image-found.jpg"
  }, {
  "title":"Ethnography and Virtual Worlds: A Handbook of Method",
  "authors":["Tom Boellstorff","Bonnie Nardi"],
  "image":"http://www.jordans.com/~/media/Jordans%20Redesign/No-image-found.jpg"
  }, {
  "title":"Understanding Digital Culture",
  "authors":["Vincent Miller"],
  "image":"http://www.jordans.com/~/media/Jordans%20Redesign/No-image-found.jpg"
  }, {
  "title":"Fixing Families: Parents, Power, and the Child Welfare System",
  "authors":["Jennifer A. Reich"],
  "image":"http://www.jordans.com/~/media/Jordans%20Redesign/No-image-found.jpg"
  }, {
  "title":"A World of Ideas: Essential Readings for College Writers",
  "authors":["Lee A. Jacobus"],
  "image":"http://www.jordans.com/~/media/Jordans%20Redesign/No-image-found.jpg"
  }, {
  "title":"The Spirit Catches You and You Fall Down: A Hmong Child, Her American Doctors, and the Collision of Two Cultures",
  "authors":["Anne Fadiman"],
  "image":"http://www.jordans.com/~/media/Jordans%20Redesign/No-image-found.jpg"
  }, {
  "title":"Warring Souls: Youth, Media, and Martyrdom in Post-Revolution Iran",
  "authors":["Roxanne Varzi"],
  "image":"http://www.jordans.com/~/media/Jordans%20Redesign/No-image-found.jpg"
  }, {
  "title":"Machines as the Measure of Men: Science, Technology, and Ideologies of Western Dominance",
  "authors":["Michael Adas"],
  "image":"http://www.jordans.com/~/media/Jordans%20Redesign/No-image-found.jpg"
  }, {
  "title":"Remix: Making Art and Commerce Thrive in the Hybrid Economy",
  "authors":["Lawrence Lessig"],
  "image":"http://www.jordans.com/~/media/Jordans%20Redesign/No-image-found.jpg"
  }, {
  "title":"Crowdsourcing",
  "authors":["Daren C. Brabham"],
  "image":"http://www.jordans.com/~/media/Jordans%20Redesign/No-image-found.jpg"
  }, {
  "title":"Big Data: A Revolution That Will Transform How We Live, Work, and Think",
  "authors":["Viktor Mayer-Schönberger","Kenneth Cukier"],
  "image":"http://www.jordans.com/~/media/Jordans%20Redesign/No-image-found.jpg"
  }, {
  "title":"What If?: Serious Scientific Answers to Absurd Hypothetical Questions",
  "authors":["Randall Munroe"],
  "image":"http://www.jordans.com/~/media/Jordans%20Redesign/No-image-found.jpg"
  }, {
  "title":"Seductions Of Crime: Moral And Sensual Attractions In Doing Evil",
  "authors":["Jack Katz"],
  "image":"http://www.jordans.com/~/media/Jordans%20Redesign/No-image-found.jpg"
  }, {
  "title":"St. Thomas Aquinas on Politics and Ethics",
  "authors":["Thomas Aquinas","Paul E. Sigmund"],
  "image":"http://www.jordans.com/~/media/Jordans%20Redesign/No-image-found.jpg"
  }, {
  "title":"The Antichrist",
  "authors":["Friedrich Nietzsche"],
  "image":"http://www.jordans.com/~/media/Jordans%20Redesign/No-image-found.jpg"
  }, {
  "title":"Psychopathic Disorders",
  "authors":["Michael Craft"],
  "image":"http://www.jordans.com/~/media/Jordans%20Redesign/No-image-found.jpg"
  }, {
  "title":"Sway: The Irresistible Pull of Irrational Behavior",
  "authors":["Ori Brafman","Rom Brafman"],
  "image":"http://www.jordans.com/~/media/Jordans%20Redesign/No-image-found.jpg"
  }, {
  "title":"The Marshmallow Test: Why Self-Control Is the Engine of Success",
  "authors":["Walter Mischel"],
  "image":"http://www.jordans.com/~/media/Jordans%20Redesign/No-image-found.jpg"
  }, {
  "title":"Seeing What Others Don't: The Remarkable Ways We Gain Insights",
  "authors":["Gary Klein"],
  "image":"http://www.jordans.com/~/media/Jordans%20Redesign/No-image-found.jpg"
  }, {
  "title":"The Drunkard's Walk: How Randomness Rules Our Lives",
  "authors":["Leonard Mlodinow"],
  "image":"http://www.jordans.com/~/media/Jordans%20Redesign/No-image-found.jpg"
  }, {
  "title":"Who Controls the Internet?: Illusions of a Borderless World",
  "authors":["Jack Goldsmith","Tim Wu"],
  "image":"http://www.jordans.com/~/media/Jordans%20Redesign/No-image-found.jpg"
  }, {
  "title":"Delete: The Virtue of Forgetting in the Digital Age",
  "authors":["Viktor Mayer-Schönberger"],
  "image":"http://www.jordans.com/~/media/Jordans%20Redesign/No-image-found.jpg"
  }, {
  "title":"Close to the Machine: Technophilia and Its Discontents",
  "authors":["Ellen Ullman"],
  "image":"http://www.jordans.com/~/media/Jordans%20Redesign/No-image-found.jpg"
  }, {
  "title":"How to Write a Lot: A Practical Guide to Productive Academic Writing",
  "authors":["Paul J. Silvia"],
  "image":"http://www.jordans.com/~/media/Jordans%20Redesign/No-image-found.jpg"
  }, {
  "title":"Reading in the Brain: The New Science of How We Read",
  "authors":["Stanislas Dehaene"],
  "image":"http://www.jordans.com/~/media/Jordans%20Redesign/No-image-found.jpg"
  }, {
  "title":"Social Psychology",
  "authors":["Richard Tracy LaPiere","Paul Randolph Farnsworth"],
  "image":"http://www.jordans.com/~/media/Jordans%20Redesign/No-image-found.jpg"
  }, {
  "title":"Psychology",
  "authors":["Henry Gleitman","James Gross","Daniel Reisberg"],
  "image":"http://www.jordans.com/~/media/Jordans%20Redesign/No-image-found.jpg"
  }, {
  "title":"Down by the Bay: San Francisco's History between the Tides",
  "authors":["Matthew Morse Booker"],
  "image":"http://www.jordans.com/~/media/Jordans%20Redesign/No-image-found.jpg"
  }, {
  "title":"How Google Works",
  "authors":["Eric Schmidt","Jonathan Rosenberg"],
  "image":"http://www.jordans.com/~/media/Jordans%20Redesign/No-image-found.jpg"
  }, {
  "title":"The Monkey's Voyage: How Improbable Journeys Shaped the History of Life",
  "authors":["Alan de Queiroz"],
  "image":"http://www.jordans.com/~/media/Jordans%20Redesign/No-image-found.jpg"
  }, {
  "title":"Sons of the Profits: There's No Business Like Grow Business. The Seattle Story, 1851-1901",
  "authors":["William C. Speidel"],
  "image":"http://www.jordans.com/~/media/Jordans%20Redesign/No-image-found.jpg"
  }, {
  "title":"Fear on Trial",
  "authors":["John Henry Faulk"],
  "image":"http://www.jordans.com/~/media/Jordans%20Redesign/No-image-found.jpg"
  }, {
  "title":"Doc Maynard: The Man Who Invented Seattle",
  "authors":["Speidel Bill"],
  "image":"http://www.jordans.com/~/media/Jordans%20Redesign/No-image-found.jpg"
  }, {
  "title":"Cengage Advantage Books: Liberty, Equality, Power: A History of the American People, Volume 1: To 1877",
  "authors":["John M. Murrin","Paul E. Johnson"],
  "image":"http://www.jordans.com/~/media/Jordans%20Redesign/No-image-found.jpg"
  }, {
  "title":"Readings in Ancient Greek Philosophy: From Thales to Aristotle",
  "authors":["S. Marc Cohen","Patricia Curd"],
  "image":"http://www.jordans.com/~/media/Jordans%20Redesign/No-image-found.jpg"
  }, {
  "title":"Writers INC: A Student Handbook for Writing and Learning",
  "authors":["Patrick Sebranek","Dave Kemper"],
  "image":"http://www.jordans.com/~/media/Jordans%20Redesign/No-image-found.jpg"
  }, {
  "title":"Literature and the Writing Process",
  "authors":["Elizabeth McMahan","Susan X. Day","Robert W. Funk"],
  "image":"http://www.jordans.com/~/media/Jordans%20Redesign/No-image-found.jpg"
  }, {
  "title":"The Nothing that Is: A Natural History of Zero",
  "authors":["Robert Kaplan","Ellen Kaplan"],
  "image":"http://www.jordans.com/~/media/Jordans%20Redesign/No-image-found.jpg"
  }, {
  "title":"East of Eden",
  "authors":["John Steinbeck"],
  "image":"http://www.jordans.com/~/media/Jordans%20Redesign/No-image-found.jpg"
  }
]